fastapi_migrations/__init__.py
fastapi_migrations/cli.py
fastapi_migrations/lib.py
fastapi_migrations/templates/default/README
fastapi_migrations/templates/default/alembic.ini.mako
fastapi_migrations/templates/default/env.py
fastapi_migrations/templates/default/script.py.mako
fastapi_migrations-0.0.5.dist-info/LICENSE
fastapi_migrations-0.0.5.dist-info/METADATA
fastapi_migrations-0.0.5.dist-info/WHEEL
fastapi_migrations-0.0.5.dist-info/top_level.txt
fastapi_migrations-0.0.5.dist-info/RECORD
