Metadata-Version: 2.1
Name: fastapi-migrations
Version: 0.0.5
Summary: A small integration between Fastapi and Alembic.
Home-page: https://github.com/patiprecios/fastapi-migrations
Author: Ariel Carvajal
Author-email: arie.cbpro@gmail.com
License: MIT
Project-URL: Code, https://github.com/patiprecios/fastapi-migrations
Project-URL: Issues, https://github.com/patiprecios/fastapi-migrations/issues
Platform: any
Classifier: Environment :: Web Environment
Classifier: Intended Audience :: Developers
Classifier: License :: OSI Approved :: MIT License
Classifier: Operating System :: OS Independent
Classifier: Programming Language :: Python
Classifier: Programming Language :: Python :: 3
Classifier: Topic :: Internet :: WWW/HTTP :: Dynamic Content
Classifier: Topic :: Software Development :: Libraries :: Python Modules
Requires-Dist: python
Requires-Dist: alembic
Requires-Dist: typer
Requires-Dist: pydantic
